poetry_src_layout/__init__.py
poetry_src_layout/main.py
poetry_src_layout/validator.py
poetry_src_layout-0.1.0.dist-info/METADATA
poetry_src_layout-0.1.0.dist-info/WHEEL
poetry_src_layout-0.1.0.dist-info/RECORD
